jupyter_server_parameters/__init__.py
jupyter_server_parameters/config.py
jupyter_server_parameters/handlers.py
jupyter_server_parameters/utils.py
jupyter_server_parameters-0.1.2.data/data/etc/jupyter/jupyter_server_config.d/jupyter_server_parameters.json
jupyter_server_parameters-0.1.2.dist-info/LICENSE
jupyter_server_parameters-0.1.2.dist-info/METADATA
jupyter_server_parameters-0.1.2.dist-info/WHEEL
jupyter_server_parameters-0.1.2.dist-info/top_level.txt
jupyter_server_parameters-0.1.2.dist-info/RECORD
