Metadata-Version: 2.1
Name: jupyter-server-parameters
Version: 0.1.2
Summary: Jupyter Server Extension to handle arbitrary URL parameter
Home-page: https://github.com/agoose77/jupyter-server-parameters
Author: Angus Hollands
Author-email: goosey15@gmail.com
License: BSD-3-Clause
Project-URL: Bug Tracker, https://github.com/agoose77/jupyter-server-parameters/issues
Keywords: binder,jupyter,parameters,jupyter-server,server-extension
Platform: Any
Classifier: Development Status :: 4 - Beta
Classifier: Intended Audience :: Developers
Classifier: Intended Audience :: Science/Research
Classifier: License :: OSI Approved :: BSD License
Classifier: Operating System :: OS Independent
Classifier: Programming Language :: Python
Classifier: Programming Language :: Python :: 3
Classifier: Programming Language :: Python :: 3 :: Only
Classifier: Programming Language :: Python :: 3.7
Classifier: Programming Language :: Python :: 3.8
Classifier: Programming Language :: Python :: 3.9
Requires-Python: >=3.7
Requires-Dist: jupyter-server (>=1.0)
